MoguiYuehuixueVer3/README.md
MoguiYuehuixueVer3/__init__.py
MoguiYuehuixueVer3/__main__.py
MoguiYuehuixueVer3/file.epub
MoguiYuehuixueVer3/index.html
MoguiYuehuixueVer3/css/__init__.py
MoguiYuehuixueVer3/css/annotations.css
MoguiYuehuixueVer3/css/main.css
MoguiYuehuixueVer3/css/normalize.css
MoguiYuehuixueVer3/css/popup.css
MoguiYuehuixueVer3/font/__init__.py
MoguiYuehuixueVer3/font/fontello.eot
MoguiYuehuixueVer3/font/fontello.svg
MoguiYuehuixueVer3/font/fontello.ttf
MoguiYuehuixueVer3/font/fontello.woff
MoguiYuehuixueVer3/img/__init__.py
MoguiYuehuixueVer3/img/annotator-glyph-sprite.png
MoguiYuehuixueVer3/img/annotator-icon-sprite.png
MoguiYuehuixueVer3/img/apple-touch-icon.png
MoguiYuehuixueVer3/img/cancelfullscreen.png
MoguiYuehuixueVer3/img/close.png
MoguiYuehuixueVer3/img/fullscreen.png
MoguiYuehuixueVer3/img/loader.gif
MoguiYuehuixueVer3/img/menu-icon.png
MoguiYuehuixueVer3/img/save.png
MoguiYuehuixueVer3/img/saved.png
MoguiYuehuixueVer3/img/settings-s.png
MoguiYuehuixueVer3/img/settings.png
MoguiYuehuixueVer3/img/star.png
MoguiYuehuixueVer3/js/__init__.py
MoguiYuehuixueVer3/js/epub.js
MoguiYuehuixueVer3/js/epub.min.js
MoguiYuehuixueVer3/js/epub.min.map
MoguiYuehuixueVer3/js/hooks.min.js
MoguiYuehuixueVer3/js/hooks.min.map
MoguiYuehuixueVer3/js/reader.js
MoguiYuehuixueVer3/js/reader.js.map
MoguiYuehuixueVer3/js/reader.min.js
MoguiYuehuixueVer3/js/reader.min.map
MoguiYuehuixueVer3/js/hooks/__init__.py
MoguiYuehuixueVer3/js/hooks/extensions/__init__.py
MoguiYuehuixueVer3/js/hooks/extensions/highlight.js
MoguiYuehuixueVer3/js/libs/__init__.py
MoguiYuehuixueVer3/js/libs/jquery.min.js
MoguiYuehuixueVer3/js/libs/localforage.min.js
MoguiYuehuixueVer3/js/libs/screenfull.js
MoguiYuehuixueVer3/js/libs/screenfull.min.js
MoguiYuehuixueVer3/js/libs/zip.min.js
MoguiYuehuixueVer3/js/plugins/__init__.py
MoguiYuehuixueVer3/js/plugins/hypothesis.js
MoguiYuehuixueVer3/js/plugins/search.js
mogui_yuehuixue_ver3-2022.10.11.0.dist-info/METADATA
mogui_yuehuixue_ver3-2022.10.11.0.dist-info/WHEEL
mogui_yuehuixue_ver3-2022.10.11.0.dist-info/entry_points.txt
mogui_yuehuixue_ver3-2022.10.11.0.dist-info/top_level.txt
mogui_yuehuixue_ver3-2022.10.11.0.dist-info/RECORD
